theano-hf/__init__.py
theano_hf/__init__.py
theanohf/__init__.py
theano_hf-0.2.1.dist-info/LICENSE.txt
theano_hf-0.2.1.dist-info/METADATA
theano_hf-0.2.1.dist-info/WHEEL
theano_hf-0.2.1.dist-info/top_level.txt
theano_hf-0.2.1.dist-info/RECORD
