Metadata-Version: 2.1
Name: theano-hf
Version: 0.2.1
Summary: General purpose Hessian-free optimization in Theano
Home-page: https://github.com/KiruyaMomochi/theano-hf-py3
Author: Kiruya Momochi
Author-email: kyaru@cock.li
License: UNKNOWN
Platform: UNKNOWN
Classifier: Programming Language :: Python :: 3
Classifier: Operating System :: OS Independent
Requires-Python: >=3.6
Requires-Dist: theano
Requires-Dist: numpy
